{
  "objects": [
    {
      "type": "sphere",
      "radius": 100,
      "center": [0, -100.5, -4],
      "material": {
        "type": "lambertian",
        "albedo": [0.0, 0.75, 0.0]
      }
    },
    {
      "type": "sphere",
      "radius": 0.5,
      "center": [-2, 0, -3],
      "material": {
        "type": "lambertian",
        "albedo": [0.9, 0.1, 0.1]
      }
    },
    {
      "type": "sphere",
      "radius": 0.2,
      "center": [-1.3, -0.3, -3],
      "material": {
        "type": "dielectric",
        "refractionIndex": 1.4
      }
    },
    {
      "type": "sphere",
      "radius": 0.5,
      "center": [-1, 0, -3.5],
      "material": {
        "type": "metal",
        "albedo": [0.2, 0.4, 0.8],
        "fuzz": 1.0
      }
    },
    {
      "type": "sphere",
      "radius": 0.5,
      "center": [0, 0, -4],
      "material": {
        "type": "dielectric",
        "refractionIndex": 1.4
      }
    },
    {
      "type": "sphere",
      "radius": 0.4,
      "center": [0, 0, -4],
      "material": {
        "type": "dielectric",
        "refractionIndex": 0.714
      }
    },
    {
      "type": "sphere",
      "radius": 0.5,
      "center": [1, 0, -3.5],
      "material": {
        "type": "metal",
        "albedo": [0.8, 0.8, 0.8],
        "fuzz": 0.5
      }
    },
    {
      "type": "sphere",
      "radius": 0.2,
      "center": [1.3, -0.3, -3],
      "material": {
        "type": "dielectric",
        "refractionIndex": 1.4
      }
    },
    {
      "type": "sphere",
      "radius": 0.5,
      "center": [2, 0, -3],
      "material": {
        "type": "metal",
        "albedo": [0.8, 0.8, 0.8],
        "fuzz": 0.01
      }
    }
  ]
}